ffsas/__init__.py
ffsas/system.py
ffsas/utils.py
ffsas/models/__init__.py
ffsas/models/base.py
ffsas/models/cylinder.py
ffsas/models/ellipsoid.py
ffsas/models/sphere.py
ffsas-1.1.5.dist-info/LICENSE
ffsas-1.1.5.dist-info/METADATA
ffsas-1.1.5.dist-info/WHEEL
ffsas-1.1.5.dist-info/top_level.txt
ffsas-1.1.5.dist-info/RECORD
