Metadata-Version: 2.1
Name: ffsas
Version: 1.1.5
Summary: Free-form inversion for small-angle scattering
Home-page: UNKNOWN
Author: Kuangdai Leng, Steve King, Tim Snow, Sarah Rogers, Jeyan Thiyagalingam
Author-email: kuangdai.leng@stfc.ac.uk
License: BSD-3-Clause License
Platform: UNKNOWN
Requires-Dist: h5py
Requires-Dist: scipy
Requires-Dist: numpy
Requires-Dist: torch (>=1.8.1)
